experiments/__init__.py
experiments/donut.py
experiments/burger/__init__.py
experiments/burger/data_generation_ar.py
experiments/burger/data_generation_pidon.py
experiments/burger/inference.py
experiments/burger/ivp.py
experiments/burger/operators.py
experiments/burger/parareal_accuracy.py
experiments/burger/training_ar.py
experiments/burger/training_pidon.py
experiments/diffusion/__init__.py
experiments/diffusion/data_generation_ar.py
experiments/diffusion/data_generation_pidon.py
experiments/diffusion/inference.py
experiments/diffusion/ivp.py
experiments/diffusion/operators.py
experiments/diffusion/parareal_accuracy.py
experiments/diffusion/training_ar.py
experiments/diffusion/training_pidon.py
experiments/diffusion_1d/__init__.py
experiments/diffusion_1d/data_generation_ar.py
experiments/diffusion_1d/inference.py
experiments/diffusion_1d/ivp.py
experiments/diffusion_1d/operators.py
experiments/diffusion_1d/parareal_accuracy.py
experiments/diffusion_1d/plotting.py
experiments/diffusion_1d/training.py
experiments/diffusion_1d/training_ar.py
experiments/diffusion_1d/training_pidon.py
experiments/population_growth/__init__.py
experiments/population_growth/data_generation_ar.py
experiments/population_growth/data_generation_pidon.py
experiments/population_growth/inference.py
experiments/population_growth/ivp.py
experiments/population_growth/operators.py
experiments/population_growth/parareal_accuracy.py
experiments/population_growth/plotting.py
experiments/population_growth/training.py
experiments/population_growth/training_ar.py
experiments/population_growth/training_pidon.py
experiments/van_der_pol/__init__.py
experiments/van_der_pol/data_generation_ar.py
experiments/van_der_pol/data_generation_pidon.py
experiments/van_der_pol/inference.py
experiments/van_der_pol/ivp.py
experiments/van_der_pol/operators.py
experiments/van_der_pol/parareal_accuracy.py
experiments/van_der_pol/training_ar.py
experiments/van_der_pol/training_pidon.py
pararealml/__init__.py
pararealml-0.3.0.dist-info/LICENSE
pararealml-0.3.0.dist-info/METADATA
pararealml-0.3.0.dist-info/WHEEL
pararealml-0.3.0.dist-info/top_level.txt
pararealml-0.3.0.dist-info/RECORD
