Metadata-Version: 2.1
Name: pararealml
Version: 0.3.0
Summary: A machine learning boosted parallel-in-time differential equation solver framework
Home-page: https://github.com/ViktorC/PararealML
Author: Viktor Csomor
Author-email: viktor.csomor@gmail.com
License: MIT
Keywords: differential equations,finite difference,parallel-in-time,parareal,machine learning,deep learning,physics-informed neural networks,scientific computing
Platform: UNKNOWN
Classifier: Development Status :: 3 - Alpha
Classifier: Intended Audience :: Science/Research
Classifier: License :: OSI Approved :: MIT License
Classifier: Programming Language :: Python :: 3
Classifier: Programming Language :: Python :: 3.8
Classifier: Programming Language :: Python :: 3.9
Classifier: Programming Language :: Python :: 3.10
Classifier: Topic :: Scientific/Engineering
Classifier: Topic :: Scientific/Engineering :: Artificial Intelligence
Classifier: Topic :: Scientific/Engineering :: Mathematics
License-File: LICENSE
Requires-Dist: numpy (>=1.21)
Requires-Dist: scipy (>=1.7.0)
Requires-Dist: matplotlib (>=3.5.0)
Requires-Dist: sympy (>=1.6)
Requires-Dist: mpi4py (>=3.0.0)
Requires-Dist: scikit-learn (>=0.24.0)
Requires-Dist: tensorflow (>=2.0.0)
Requires-Dist: tensorflow-probability (>=0.10.0)
